periodic/__init__.py
periodic/mass.py
periodic/table.db
periodic/table.py
periodic2023-2.2.1.dist-info/METADATA
periodic2023-2.2.1.dist-info/WHEEL
periodic2023-2.2.1.dist-info/entry_points.txt
periodic2023-2.2.1.dist-info/top_level.txt
periodic2023-2.2.1.dist-info/RECORD
