Metadata-Version: 2.1
Name: periodic2023
Version: 2.2.1
Summary: A periodic table API.
Home-page: https://github.com/NMRbox/periodic.git
Author: Jose Luis Naranjo Gomez
Author-email: luisnaranjo733@hotmail.com
Maintainer: Gerard Weatherby / NMRbox
Maintainer-email: gweatherby@uchc.edu
License: GNU GPL
Keywords: chem chemistry periodic table finder elements
Classifier: License :: OSI Approved :: GNU General Public License (GPL)
Classifier: Topic :: Utilities
Requires-Dist: SQLAlchemy (==0.7.7)
